izakaya/__init__.py
izakaya/__version__.py
izakaya/py.typed
izakaya-0.0.1.dist-info/LICENSE
izakaya-0.0.1.dist-info/WHEEL
izakaya-0.0.1.dist-info/METADATA
izakaya-0.0.1.dist-info/RECORD
