Metadata-Version: 2.1
Name: izakaya
Version: 0.0.1
Summary: Real time event sourcing and application state management in a distributed computing context
Home-page: https://github.com/kalaspuff/izakaya
License: MIT
Keywords: izakaya,event sourcing,cqrs,events,distributed data
Author: Carl Oscar Aaro
Author-email: hello@carloscar.com
Requires-Python: >=3.6,<4.0
Classifier: Development Status :: 1 - Planning
Classifier: Framework :: AsyncIO
Classifier: Intended Audience :: Developers
Classifier: License :: OSI Approved :: MIT License
Classifier: Programming Language :: Python
Classifier: Programming Language :: Python :: 3
Classifier: Programming Language :: Python :: 3.6
Classifier: Programming Language :: Python :: 3.7
Classifier: Programming Language :: Python :: 3.8
Classifier: Topic :: Software Development
Classifier: Topic :: Software Development :: Libraries
Classifier: Typing :: Typed
Project-URL: Repository, https://github.com/kalaspuff/izakaya
